airline_reservation_system/__init__.py
airline_reservation_system/__main__.py
airline_reservation_system/admin.py
airline_reservation_system/booking.py
airline_reservation_system/db.py
airline_reservation_system/flight.py
airline_reservation_system/main.py
airline_reservation_system/user.py
airline_reservation_system-0.1.0.dist-info/METADATA
airline_reservation_system-0.1.0.dist-info/WHEEL
airline_reservation_system-0.1.0.dist-info/RECORD
