Metadata-Version: 2.3
Name: airline-reservation-system
Version: 0.1.0
Summary: A console-based Airline Reservation System in Python
License: MIT
Author: Your Name
Author-email: you@example.com
Requires-Python: >=3.13,<4.0
Classifier: License :: OSI Approved :: MIT License
Classifier: Programming Language :: Python :: 3
Classifier: Programming Language :: Python :: 3.13
Requires-Dist: click (>=8.1.7,<9.0.0)
Requires-Dist: pandas (>=2.2.2,<3.0.0)
Requires-Dist: pymongo (>=4.9.0,<5.0.0)
Requires-Dist: rich (>=13.7.1,<14.0.0)
Requires-Dist: sqlalchemy (>=2.0.30,<3.0.0)
